{
  "date": "2016-12-31",
  "latitude": 33.3560276,
  "longitude": -111.7443246,
  "timezone": "America/Phoenix",
  "currently": {
    "time": "1584576000000",
    "summary": "Rain",
    "icon": "rain",
    "precipIntensity": 0.1277,
    "precipProbability": 0.8,
    "precipType": "rain",
    "temperature": 57.52,
    "apparentTemperature": 57.52,
    "dewPoint": 47.17,
    "humidity": 0.68,
    "pressure": 1006,
    "windSpeed": 12.01,
    "windGust": 20.38,
    "windBearing": 165,
    "cloudCover": 0.97,
    "uvIndex": 1,
    "visibility": 4.218,
    "ozone": 345.8
  },
  "hourly": {
    "summary": "Rain in the afternoon and evening.",
    "icon": "rain",
    "data": [
      {
        "time": "1584514800000",
        "summary": "Clear",
        "icon": "clear-night",
        "precipIntensity": 0,
        "precipProbability": 0,
        "temperature": 60.93,
        "apparentTemperature": 60.93,
        "dewPoint": 43.4,
        "humidity": 0.52,
        "pressure": 1012.2,
        "windSpeed": 4.62,
        "windGust": 6.98,
        "windBearing": 171,
        "cloudCover": 0.08,
        "uvIndex": 0,
        "visibility": 10,
        "ozone": 322.9
      },
      {
        "time": "1584518400000",
        "summary": "Clear",
        "icon": "clear-night",
        "precipIntensity": 0.0016,
        "precipProbability": 0.01,
        "precipType": "rain",
        "temperature": 59.36,
        "apparentTemperature": 59.36,
        "dewPoint": 41.85,
        "humidity": 0.52,
        "pressure": 1012.5,
        "windSpeed": 4.89,
        "windGust": 8.2,
        "windBearing": 172,
        "cloudCover": 0.1,
        "uvIndex": 0,
        "visibility": 10,
        "ozone": 321
      },
      {
        "time": "1584522000000",
        "summary": "Clear",
        "icon": "clear-night",
        "precipIntensity": 0,
        "precipProbability": 0,
        "temperature": 58.19,
        "apparentTemperature": 58.19,
        "dewPoint": 42.39,
        "humidity": 0.56,
        "pressure": 1012.3,
        "windSpeed": 3.18,
        "windGust": 6.48,
        "windBearing": 174,
        "cloudCover": 0.15,
        "uvIndex": 0,
        "visibility": 10,
        "ozone": 320.4
      },
      {
        "time": "1584525600000",
        "summary": "Clear",
        "icon": "clear-night",
        "precipIntensity": 0.0005,
        "precipProbability": 0.01,
        "precipType": "rain",
        "temperature": 56.49,
        "apparentTemperature": 56.49,
        "dewPoint": 43.05,
        "humidity": 0.61,
        "pressure": 1012,
        "windSpeed": 4.49,
        "windGust": 4.66,
        "windBearing": 149,
        "cloudCover": 0.21,
        "uvIndex": 0,
        "visibility": 10,
        "ozone": 322.4
      },
      {
        "time": "1584529200000",
        "summary": "Clear",
        "icon": "clear-night",
        "precipIntensity": 0.0023,
        "precipProbability": 0.02,
        "precipType": "rain",
        "temperature": 56.36,
        "apparentTemperature": 56.36,
        "dewPoint": 42.33,
        "humidity": 0.59,
        "pressure": 1011.8,
        "windSpeed": 4.47,
        "windGust": 4.47,
        "windBearing": 131,
        "cloudCover": 0.23,
        "uvIndex": 0,
        "visibility": 10,
        "ozone": 325.7
      },
      {
        "time": "1584532800000",
        "summary": "Clear",
        "icon": "clear-night",
        "precipIntensity": 0.0005,
        "precipProbability": 0.01,
        "precipType": "rain",
        "temperature": 56.04,
        "apparentTemperature": 56.04,
        "dewPoint": 44.46,
        "humidity": 0.65,
        "pressure": 1011.4,
        "windSpeed": 3.62,
        "windGust": 3.62,
        "windBearing": 111,
        "cloudCover": 0.3,
        "uvIndex": 0,
        "visibility": 10,
        "ozone": 329.3
      },
      {
        "time": "1584536400000",
        "summary": "Partly Cloudy",
        "icon": "partly-cloudy-night",
        "precipIntensity": 0.0007,
        "precipProbability": 0.02,
        "precipType": "rain",
        "temperature": 55.92,
        "apparentTemperature": 55.92,
        "dewPoint": 44.11,
        "humidity": 0.64,
        "pressure": 1011.3,
        "windSpeed": 3.5,
        "windGust": 4.95,
        "windBearing": 98,
        "cloudCover": 0.39,
        "uvIndex": 0,
        "visibility": 10,
        "ozone": 333.1
      },
      {
        "time": "1584540000000",
        "summary": "Partly Cloudy",
        "icon": "partly-cloudy-day",
        "precipIntensity": 0.0003,
        "precipProbability": 0.03,
        "precipType": "rain",
        "temperature": 57.56,
        "apparentTemperature": 57.56,
        "dewPoint": 42.83,
        "humidity": 0.58,
        "pressure": 1011.3,
        "windSpeed": 2.84,
        "windGust": 4.05,
        "windBearing": 88,
        "cloudCover": 0.42,
        "uvIndex": 0,
        "visibility": 10,
        "ozone": 336.9
      },
      {
        "time": "1584543600000",
        "summary": "Partly Cloudy",
        "icon": "partly-cloudy-day",
        "precipIntensity": 0.0015,
        "precipProbability": 0.05,
        "precipType": "rain",
        "temperature": 58.14,
        "apparentTemperature": 58.14,
        "dewPoint": 44.27,
        "humidity": 0.6,
        "pressure": 1011.4,
        "windSpeed": 4.03,
        "windGust": 6.03,
        "windBearing": 114,
        "cloudCover": 0.45,
        "uvIndex": 1,
        "visibility": 10,
        "ozone": 339.3
      },
      {
        "time": "1584547200000",
        "summary": "Partly Cloudy",
        "icon": "partly-cloudy-day",
        "precipIntensity": 0.0024,
        "precipProbability": 0.06,
        "precipType": "rain",
        "temperature": 59.34,
        "apparentTemperature": 59.34,
        "dewPoint": 44.25,
        "humidity": 0.57,
        "pressure": 1011.2,
        "windSpeed": 4.11,
        "windGust": 6.6,
        "windBearing": 145,
        "cloudCover": 0.5,
        "uvIndex": 2,
        "visibility": 10,
        "ozone": 339.2
      },
      {
        "time": "1584550800000",
        "summary": "Partly Cloudy",
        "icon": "partly-cloudy-day",
        "precipIntensity": 0.0021,
        "precipProbability": 0.09,
        "precipType": "rain",
        "temperature": 61.57,
        "apparentTemperature": 61.57,
        "dewPoint": 44.87,
        "humidity": 0.54,
        "pressure": 1010.5,
        "windSpeed": 4.25,
        "windGust": 6.61,
        "windBearing": 146,
        "cloudCover": 0.55,
        "uvIndex": 3,
        "visibility": 10,
        "ozone": 337.6
      },
      {
        "time": "1584554400000",
        "summary": "Partly Cloudy",
        "icon": "partly-cloudy-day",
        "precipIntensity": 0.001,
        "precipProbability": 0.02,
        "precipType": "rain",
        "temperature": 64.96,
        "apparentTemperature": 64.96,
        "dewPoint": 42,
        "humidity": 0.43,
        "pressure": 1009.8,
        "windSpeed": 6.51,
        "windGust": 11.48,
        "windBearing": 134,
        "cloudCover": 0.46,
        "uvIndex": 5,
        "visibility": 10,
        "ozone": 334.9
      },
      {
        "time": "1584558000000",
        "summary": "Partly Cloudy",
        "icon": "partly-cloudy-day",
        "precipIntensity": 0.0031,
        "precipProbability": 0.06,
        "precipType": "rain",
        "temperature": 66.65,
        "apparentTemperature": 66.65,
        "dewPoint": 42.48,
        "humidity": 0.41,
        "pressure": 1009,
        "windSpeed": 9.01,
        "windGust": 14.85,
        "windBearing": 151,
        "cloudCover": 0.54,
        "uvIndex": 5,
        "visibility": 10,
        "ozone": 333.6
      },
      {
        "time": "1584561600000",
        "summary": "Partly Cloudy",
        "icon": "partly-cloudy-day",
        "precipIntensity": 0.009,
        "precipProbability": 0.13,
        "precipType": "rain",
        "temperature": 67.03,
        "apparentTemperature": 67.03,
        "dewPoint": 42.45,
        "humidity": 0.41,
        "pressure": 1008,
        "windSpeed": 8.38,
        "windGust": 13.97,
        "windBearing": 157,
        "cloudCover": 0.57,
        "uvIndex": 5,
        "visibility": 10,
        "ozone": 332.6
      },
      {
        "time": "1584565200000",
        "summary": "Possible Light Rain",
        "icon": "rain",
        "precipIntensity": 0.0192,
        "precipProbability": 0.31,
        "precipType": "rain",
        "temperature": 66.29,
        "apparentTemperature": 66.29,
        "dewPoint": 45.1,
        "humidity": 0.46,
        "pressure": 1007.1,
        "windSpeed": 8.11,
        "windGust": 13.24,
        "windBearing": 188,
        "cloudCover": 0.74,
        "uvIndex": 4,
        "visibility": 10,
        "ozone": 333.2
      },
      {
        "time": "1584568800000",
        "summary": "Possible Light Rain",
        "icon": "rain",
        "precipIntensity": 0.0345,
        "precipProbability": 0.48,
        "precipType": "rain",
        "temperature": 60.26,
        "apparentTemperature": 60.26,
        "dewPoint": 50.69,
        "humidity": 0.71,
        "pressure": 1006.2,
        "windSpeed": 5.88,
        "windGust": 7.78,
        "windBearing": 223,
        "cloudCover": 0.69,
        "uvIndex": 3,
        "visibility": 10,
        "ozone": 335.4
      },
      {
        "time": "1584572400000",
        "summary": "Light Rain",
        "icon": "rain",
        "precipIntensity": 0.065,
        "precipProbability": 0.73,
        "precipType": "rain",
        "temperature": 57.54,
        "apparentTemperature": 57.54,
        "dewPoint": 47.58,
        "humidity": 0.69,
        "pressure": 1006,
        "windSpeed": 12.48,
        "windGust": 14.55,
        "windBearing": 212,
        "cloudCover": 0.99,
        "uvIndex": 2,
        "visibility": 4.972,
        "ozone": 339.2
      },
      {
        "time": "1584576000000",
        "summary": "Rain",
        "icon": "rain",
        "precipIntensity": 0.1277,
        "precipProbability": 0.8,
        "precipType": "rain",
        "temperature": 57.52,
        "apparentTemperature": 57.52,
        "dewPoint": 47.17,
        "humidity": 0.68,
        "pressure": 1006,
        "windSpeed": 12.01,
        "windGust": 20.38,
        "windBearing": 165,
        "cloudCover": 0.97,
        "uvIndex": 1,
        "visibility": 4.218,
        "ozone": 345.8
      },
      {
        "time": "1584579600000",
        "summary": "Rain",
        "icon": "rain",
        "precipIntensity": 0.1343,
        "precipProbability": 0.71,
        "precipType": "rain",
        "temperature": 55.37,
        "apparentTemperature": 55.37,
        "dewPoint": 49.9,
        "humidity": 0.82,
        "pressure": 1006.8,
        "windSpeed": 9.4,
        "windGust": 15.94,
        "windBearing": 176,
        "cloudCover": 0.81,
        "uvIndex": 0,
        "visibility": 5.328,
        "ozone": 358.9
      },
      {
        "time": "1584583200000",
        "summary": "Possible Light Rain",
        "icon": "rain",
        "precipIntensity": 0.0334,
        "precipProbability": 0.44,
        "precipType": "rain",
        "temperature": 54.43,
        "apparentTemperature": 54.43,
        "dewPoint": 47.89,
        "humidity": 0.79,
        "pressure": 1008.6,
        "windSpeed": 9.2,
        "windGust": 15.67,
        "windBearing": 165,
        "cloudCover": 0.59,
        "uvIndex": 0,
        "visibility": 9.703,
        "ozone": 375
      },
      {
        "time": "1584586800000",
        "summary": "Possible Light Rain",
        "icon": "rain",
        "precipIntensity": 0.0215,
        "precipProbability": 0.37,
        "precipType": "rain",
        "temperature": 53.66,
        "apparentTemperature": 53.66,
        "dewPoint": 47.25,
        "humidity": 0.79,
        "pressure": 1009.8,
        "windSpeed": 6.33,
        "windGust": 12.69,
        "windBearing": 200,
        "cloudCover": 0.58,
        "uvIndex": 0,
        "visibility": 10,
        "ozone": 384.6
      },
      {
        "time": "1584590400000",
        "summary": "Possible Light Rain",
        "icon": "rain",
        "precipIntensity": 0.0269,
        "precipProbability": 0.36,
        "precipType": "rain",
        "temperature": 52.44,
        "apparentTemperature": 52.44,
        "dewPoint": 45.54,
        "humidity": 0.77,
        "pressure": 1010.5,
        "windSpeed": 4.72,
        "windGust": 8.44,
        "windBearing": 190,
        "cloudCover": 0.73,
        "uvIndex": 0,
        "visibility": 10,
        "ozone": 382.2
      },
      {
        "time": "1584594000000",
        "summary": "Possible Light Rain",
        "icon": "rain",
        "precipIntensity": 0.0192,
        "precipProbability": 0.4,
        "precipType": "rain",
        "temperature": 52.3,
        "apparentTemperature": 52.3,
        "dewPoint": 44.67,
        "humidity": 0.75,
        "pressure": 1011,
        "windSpeed": 7.4,
        "windGust": 13.79,
        "windBearing": 208,
        "cloudCover": 0.58,
        "uvIndex": 0,
        "visibility": 10,
        "ozone": 373.5
      },
      {
        "time": "1584597600000",
        "summary": "Partly Cloudy",
        "icon": "partly-cloudy-night",
        "precipIntensity": 0.0051,
        "precipProbability": 0.23,
        "precipType": "rain",
        "temperature": 50.55,
        "apparentTemperature": 50.55,
        "dewPoint": 44.52,
        "humidity": 0.8,
        "pressure": 1011.7,
        "windSpeed": 5.57,
        "windGust": 10.34,
        "windBearing": 184,
        "cloudCover": 0.54,
        "uvIndex": 0,
        "visibility": 10,
        "ozone": 366
      }
    ]
  },
  "daily": {
    "data": [
      {
        "time": "1584514800000",
        "summary": "Rain starting in the afternoon.",
        "icon": "rain",
        "sunriseTime": "1584538380000",
        "sunsetTime": "1584581940000",
        "moonPhase": 0.84,
        "precipIntensity": 0.0222,
        "precipIntensityMax": 0.1422,
        "precipIntensityMaxTime": 1584578280000,
        "precipProbability": 0.9,
        "precipType": "rain",
        "temperatureHigh": 67.57,
        "temperatureHighTime": "1584563100000",
        "temperatureLow": 48.94,
        "temperatureLowTime": "1584611940000",
        "apparentTemperatureHigh": 67.07,
        "apparentTemperatureHighTime": "1584563100000",
        "apparentTemperatureLow": 47.92,
        "apparentTemperatureLowTime": "1584604080000",
        "dewPoint": 44.82,
        "humidity": 0.62,
        "pressure": 1009.8,
        "windSpeed": 6.26,
        "windGust": 20.39,
        "windGustTime": "1584576120000",
        "windBearing": 167,
        "cloudCover": 0.52,
        "uvIndex": 5,
        "uvIndexTime": "1584559800000",
        "visibility": 9.336,
        "ozone": 342.5,
        "temperatureMin": 50.06,
        "temperatureMinTime": "1584597600000",
        "temperatureMax": 67.57,
        "temperatureMaxTime": "1584563100000",
        "apparentTemperatureMin": 50.55,
        "apparentTemperatureMinTime": "1584597600000",
        "apparentTemperatureMax": 67.07,
        "apparentTemperatureMaxTime": "1584563100000"
      }
    ]
  },
  "flags": {
    "sources": [
      "cmc",
      "gfs",
      "hrrr",
      "icon",
      "isd",
      "madis",
      "nam",
      "sref"
    ],
    "nearest-station": 1.755,
    "units": "us"
  },
  "offset": -7
}
